srttranslate/VERSION
srttranslate/__init__.py
srttranslate/deeplhandler.py
srttranslate/main.py
srttranslate/subtitles.py
srttranslate/translator.py
srttranslate-1.0.0.dist-info/LICENSE
srttranslate-1.0.0.dist-info/METADATA
srttranslate-1.0.0.dist-info/WHEEL
srttranslate-1.0.0.dist-info/entry_points.txt
srttranslate-1.0.0.dist-info/top_level.txt
srttranslate-1.0.0.dist-info/RECORD
