Metadata-Version: 2.1
Name: srttranslate
Version: 1.0.0
Summary: Subtitle srt file automatic translator based on deepl.com
Home-page: https://github.com/destrangis/srttranslate
Author: Javier Llopis
Author-email: javier@llopis.me
License: MIT
Platform: UNKNOWN
Classifier: Development Status :: 5 - Production/Stable
Classifier: Environment :: Console
Classifier: Intended Audience :: End Users/Desktop
Classifier: License :: OSI Approved :: MIT License
Classifier: Operating System :: OS Independent
Classifier: Programming Language :: Python :: 3 :: Only
Classifier: Topic :: Text Processing :: Linguistic
License-File: LICENSE
Requires-Dist: deepl
